Metadata-Version: 1.1
Name: furigana
Version: 0.0.7.1
Summary: Convert Japanese Kanji to Kanji attached with Hiragana. For example, 「澱んだ街角」→「澱(よど)んだ街角(まちかど)」
Home-page: https://github.com/MikimotoH/furigana
Author: Miki.Liu
Author-email: mikimotoh@gmail.com
License: UNKNOWN
Keywords: Japanese Language Processing
Platform: UNKNOWN
Classifier: Development Status :: 3 - Alpha
Classifier: Environment :: Console
Classifier: Intended Audience :: Developers
Classifier: Intended Audience :: Science/Research
Classifier: License :: OSI Approved :: MIT License
Classifier: Programming Language :: Python :: 3
Classifier: Topic :: Software Development :: Libraries :: Python Modules
Classifier: Topic :: Text Processing :: Linguistic
